apppy/fastql/__init__.py
apppy/fastql/errors.py
apppy/fastql/permissions.py
apppy/fastql/typed_id.py
apppy/fastql/typed_id_unit_test.py
apppy/fastql/annotation/__init__.py
apppy/fastql/annotation/error.py
apppy/fastql/annotation/id.py
apppy/fastql/annotation/input.py
apppy/fastql/annotation/interface.py
apppy/fastql/annotation/mutation.py
apppy/fastql/annotation/output.py
apppy/fastql/annotation/query.py
apppy_fastql-0.23.2.dist-info/METADATA
apppy_fastql-0.23.2.dist-info/WHEEL
apppy_fastql-0.23.2.dist-info/RECORD
